qry/__init__.py
qry/api/__init__.py
qry/cli/__init__.py
qry/core/__init__.py
qry/engines/__init__.py
qry/utils/__init__.py
qry/web/__init__.py
qry-0.2.1.dist-info/LICENSE
qry-0.2.1.dist-info/METADATA
qry-0.2.1.dist-info/WHEEL
qry-0.2.1.dist-info/entry_points.txt
qry-0.2.1.dist-info/RECORD
